{
  "accelerate_state_path": "/home/rishi/continuum-hydra/.hydra/state/accelerate_state.json",
  "accelerate_status": "Partial",
  "accelerate_used": true,
  "attempts": [
    {
      "checkpoint_seen": null,
      "command_argv": [
        "/home/rishi/continuum-hydra/.venv/bin/python3",
        "-u",
        "test_training/train_100m_mmfine_reason.py",
        "--max-samples",
        "500",
        "--num-train-epochs",
        "1",
        "--output-dir",
        "./outputs/mmfine_100m"
      ],
      "duration_seconds": 27.79,
      "ended_at": "2026-02-17T16:41:59.007495+00:00",
      "return_code": 1,
      "started_at": "2026-02-17T16:41:31.220904+00:00",
      "stdout_tail": [
        "                                   ^^^^^^^^^^^^^^^^^^^^^^^^^^^^^^^^^^^^^^^^^^^^^^^^^^^^^^^^^^^",
        "  File \"/home/rishi/continuum-hydra/.venv/lib/python3.12/site-packages/huggingface_hub/hf_file_system.py\", line 209, in _repo_and_revision_exist",
        "    self._api.repo_info(",
        "  File \"/home/rishi/continuum-hydra/.venv/lib/python3.12/site-packages/huggingface_hub/utils/_validators.py\", line 89, in _inner_fn",
        "    return fn(*args, **kwargs)",
        "           ^^^^^^^^^^^^^^^^^^^",
        "  File \"/home/rishi/continuum-hydra/.venv/lib/python3.12/site-packages/huggingface_hub/hf_api.py\", line 2997, in repo_info",
        "    return method(",
        "           ^^^^^^^",
        "  File \"/home/rishi/continuum-hydra/.venv/lib/python3.12/site-packages/huggingface_hub/utils/_validators.py\", line 89, in _inner_fn",
        "    return fn(*args, **kwargs)",
        "           ^^^^^^^^^^^^^^^^^^^",
        "  File \"/home/rishi/continuum-hydra/.venv/lib/python3.12/site-packages/huggingface_hub/hf_api.py\", line 2860, in dataset_info",
        "    r = get_session().get(path, headers=headers, timeout=timeout, params=params)",
        "        ^^^^^^^^^^^^^^^^^^^^^^^^^^^^^^^^^^^^^^^^^^^^^^^^^^^^^^^^^^^^^^^^^^^^^^^^",
        "  File \"/home/rishi/continuum-hydra/.venv/lib/python3.12/site-packages/httpx/_client.py\", line 1053, in get",
        "    return self.request(",
        "           ^^^^^^^^^^^^^",
        "  File \"/home/rishi/continuum-hydra/.venv/lib/python3.12/site-packages/httpx/_client.py\", line 825, in request",
        "    return self.send(request, auth=auth, follow_redirects=follow_redirects)",
        "           ^^^^^^^^^^^^^^^^^^^^^^^^^^^^^^^^^^^^^^^^^^^^^^^^^^^^^^^^^^^^^^^^",
        "  File \"/home/rishi/continuum-hydra/.venv/lib/python3.12/site-packages/httpx/_client.py\", line 914, in send",
        "    response = self._send_handling_auth(",
        "               ^^^^^^^^^^^^^^^^^^^^^^^^^",
        "  File \"/home/rishi/continuum-hydra/.venv/lib/python3.12/site-packages/httpx/_client.py\", line 942, in _send_handling_auth",
        "    response = self._send_handling_redirects(",
        "               ^^^^^^^^^^^^^^^^^^^^^^^^^^^^^^",
        "  File \"/home/rishi/continuum-hydra/.venv/lib/python3.12/site-packages/httpx/_client.py\", line 979, in _send_handling_redirects",
        "    response = self._send_single_request(request)",
        "               ^^^^^^^^^^^^^^^^^^^^^^^^^^^^^^^^^^",
        "  File \"/home/rishi/continuum-hydra/.venv/lib/python3.12/site-packages/httpx/_client.py\", line 1014, in _send_single_request",
        "    response = transport.handle_request(request)",
        "               ^^^^^^^^^^^^^^^^^^^^^^^^^^^^^^^^^",
        "  File \"/home/rishi/continuum-hydra/.venv/lib/python3.12/site-packages/httpx/_transports/default.py\", line 249, in handle_request",
        "    with map_httpcore_exceptions():",
        "  File \"/usr/lib/python3.12/contextlib.py\", line 158, in __exit__",
        "    self.gen.throw(value)",
        "  File \"/home/rishi/continuum-hydra/.venv/lib/python3.12/site-packages/httpx/_transports/default.py\", line 118, in map_httpcore_exceptions",
        "    raise mapped_exc(message) from exc",
        "httpx.ReadTimeout: The read operation timed out"
      ]
    }
  ],
  "command_argv": [
    "/home/rishi/continuum-hydra/.venv/bin/python3",
    "-u",
    "test_training/train_100m_mmfine_reason.py",
    "--max-samples",
    "500",
    "--num-train-epochs",
    "1",
    "--output-dir",
    "./outputs/mmfine_100m"
  ],
  "error": "training process exited with code 1; resume unavailable (no checkpoint discovered)",
  "exit_code": 1,
  "latest_checkpoint": null,
  "log_path": "/home/rishi/continuum-hydra/.hydra/launch/runs/launch-run-20260217164131/launch.log",
  "max_restarts": 1,
  "mode": "apply",
  "restarts_used": 0,
  "run_id": "launch-run-20260217164131",
  "schema_version": "launch.runtime.v1",
  "script": "test_training/train_100m_mmfine_reason.py",
  "script_args": [
    "--max-samples",
    "500",
    "--num-train-epochs",
    "1",
    "--output-dir",
    "./outputs/mmfine_100m"
  ],
  "status": "failed"
}
